[
  {
    "customerId_1": 2346.7757867319806,
    "statusCode": 200,
    "scenario": "successful operation"
  },
  {
    "customerId_2": 7060.530282143635,
    "statusCode": 200,
    "scenario": "successful operation"
  },
  {
    "customerId_3": 1045300,
    "statusCode": 200,
    "scenario": "successful operation"
  },
  {
    "customerId_4": 9999,
    "statusCode": 401,
    "scenario": "Error: Authorisation failed."
  },
  {
    "customerId_5": 8888,
    "statusCode": 401,
    "scenario": "Error: Authorisation failed."
  },
  {
    "customerId_6": 7777,
    "statusCode": 404,
    "scenario": "Error: Not Found"
  },
  {
    "customerId_7": 6666,
    "statusCode": 404,
    "scenario": "Error: Not Found"
  }
]