[
  {
    "accountNumber_*string": "ACC123456",
    "customerId_*string": "CUST789101",
    "ssNumber_*string": "SSN112233",
    "ssnShort_*string": "SSNS444555",
    "statusCode": 200,
    "scenario": "Success"
  },
  {
    "accountNumber_*string": "ACC654321",
    "customerId_*string": "CUST101112",
    "ssNumber_*string": "SSN445566",
    "ssnShort_*string": "SSNS777888",
    "statusCode": 401,
    "scenario": "Error: Authorisation failed."
  },
  {
    "accountNumber_*string": "ACC987654",
    "customerId_*string": "CUST131415",
    "ssNumber_*string": "SSN778899",
    "ssnShort_*string": "SSNS999000",
    "statusCode": 404,
    "scenario": "Error: Not Found"
  },
  {
    "accountNumber_*string": "ACC246810",
    "customerId_*string": "CUST161718",
    "ssNumber_*string": "SSN001122",
    "ssnShort_*string": "SSNS223344",
    "statusCode": 200,
    "scenario": "Success"
  },
  {
    "accountNumber_*string": "ACC135791",
    "customerId_*string": "CUST192021",
    "ssNumber_*string": "SSN334455",
    "ssnShort_*string": "SSNS556677",
    "statusCode": 401,
    "scenario": "Error: Authorisation failed."
  }
]