[
  {
    "koreUserId": "user1",
    "botId": "bot1",
    "accountId": "acc1",
    "accountName": "Account1",
    "accountNumber": [
      "1042345"
    ],
    "customerId": 1045300,
    "description": "Internal Transfer",
    "requestSubType": "subType1",
    "requestType": "type1",
    "serviceType": "service1",
    "statusCode": 200,
    "scenario": "success"
  },
  {
    "koreUserId": "user2",
    "botId": "bot2",
    "accountId": "acc2",
    "accountName": "Account2",
    "accountNumber": [
      "1042346"
    ],
    "customerId": 1045301,
    "description": "Internal Transfer",
    "requestSubType": "subType2",
    "requestType": "type2",
    "serviceType": "service2",
    "statusCode": 200,
    "scenario": "success"
  },
  {
    "koreUserId": "user3",
    "botId": "bot3",
    "accountId": "acc3",
    "accountName": "Account3",
    "accountNumber": [
      "1042347"
    ],
    "customerId": 1045302,
    "description": "Internal Transfer",
    "requestSubType": "subType3",
    "requestType": "type3",
    "serviceType": "service3",
    "statusCode": 200,
    "scenario": "success"
  },
  {
    "koreUserId": "user4",
    "botId": "bot4",
    "accountId": "acc4",
    "accountName": "Account4",
    "accountNumber": [
      "1042348"
    ],
    "customerId": 1045303,
    "description": "Internal Transfer",
    "requestSubType": "subType4",
    "requestType": "type4",
    "serviceType": "service4",
    "statusCode": 401,
    "scenario": "Error: Authorisation failed."
  },
  {
    "koreUserId": "user5",
    "botId": "bot5",
    "accountId": "acc5",
    "accountName": "Account5",
    "accountNumber": [
      "1042349"
    ],
    "customerId": 1045304,
    "description": "Internal Transfer",
    "requestSubType": "subType5",
    "requestType": "type5",
    "serviceType": "service5",
    "statusCode": 401,
    "scenario": "Error: Authorisation failed."
  },
  {
    "koreUserId": "user6",
    "botId": "bot6",
    "accountId": "acc6",
    "accountName": "Account6",
    "accountNumber": [
      "1042350"
    ],
    "customerId": 1045305,
    "description": "Internal Transfer",
    "requestSubType": "subType6",
    "requestType": "type6",
    "serviceType": "service6",
    "statusCode": 401,
    "scenario": "Error: Authorisation failed."
  },
  {
    "koreUserId": "user7",
    "botId": "bot7",
    "accountId": "acc7",
    "accountName": "Account7",
    "accountNumber": [
      "1042351"
    ],
    "customerId": 1045306,
    "description": "Internal Transfer",
    "requestSubType": "subType7",
    "requestType": "type7",
    "serviceType": "service7",
    "statusCode": 404,
    "scenario": "Error: Not Found"
  },
  {
    "koreUserId": "user8",
    "botId": "bot8",
    "accountId": "acc8",
    "accountName": "Account8",
    "accountNumber": [
      "1042352"
    ],
    "customerId": 1045307,
    "description": "Internal Transfer",
    "requestSubType": "subType8",
    "requestType": "type8",
    "serviceType": "service8",
    "statusCode": 404,
    "scenario": "Error: Not Found"
  },
  {
    "koreUserId": "user9",
    "botId": "bot9",
    "accountId": "acc9",
    "accountName": "Account9",
    "accountNumber": [
      "1042353"
    ],
    "customerId": 1045308,
    "description": "Internal Transfer",
    "requestSubType": "subType9",
    "requestType": "type9",
    "serviceType": "service9",
    "statusCode": 404,
    "scenario": "Error: Not Found"
  },
  {
    "koreUserId": "user10",
    "botId": "bot10",
    "accountId": "acc10",
    "accountName": "Account10",
    "accountNumber": [
      "1042354"
    ],
    "customerId": 1045309,
    "description": "Internal Transfer",
    "requestSubType": "subType10",
    "requestType": "type10",
    "serviceType": "service10",
    "statusCode": 200,
    "scenario": "success"
  },
  {
    "koreUserId": "user11",
    "botId": "bot11",
    "accountId": "acc11",
    "accountName": "Account11",
    "accountNumber": [
      "1042355"
    ],
    "customerId": 1045310,
    "description": "Internal Transfer",
    "requestSubType": "subType11",
    "requestType": "type11",
    "serviceType": "service11",
    "statusCode": 200,
    "scenario": "success"
  },
  {
    "koreUserId": "user12",
    "botId": "bot12",
    "accountId": "acc12",
    "accountName": "Account12",
    "accountNumber": [
      "1042356"
    ],
    "customerId": 1045311,
    "description": "Internal Transfer",
    "requestSubType": "subType12",
    "requestType": "type12",
    "serviceType": "service12",
    "statusCode": 200,
    "scenario": "success"
  },
  {
    "koreUserId": "user13",
    "botId": "bot13",
    "accountId": "acc13",
    "accountName": "Account13",
    "accountNumber": [
      "1042357"
    ],
    "customerId": 1045312,
    "description": "Internal Transfer",
    "requestSubType": "subType13",
    "requestType": "type13",
    "serviceType": "service13",
    "statusCode": 401,
    "scenario": "Error: Authorisation failed."
  },
  {
    "koreUserId": "user14",
    "botId": "bot14",
    "accountId": "acc14",
    "accountName": "Account14",
    "accountNumber": [
      "1042358"
    ],
    "customerId": 1045313,
    "description": "Internal Transfer",
    "requestSubType": "subType14",
    "requestType": "type14",
    "serviceType": "service14",
    "statusCode": 401,
    "scenario": "Error: Authorisation failed."
  },
  {
    "koreUserId": "user15",
    "botId": "bot15",
    "accountId": "acc15",
    "accountName": "Account15",
    "accountNumber": [
      "1042359"
    ],
    "customerId": 1045314,
    "description": "Internal Transfer",
    "requestSubType": "subType15",
    "requestType": "type15",
    "serviceType": "service15",
    "statusCode": 401,
    "scenario": "Error: Authorisation failed."
  }
]